Metadata-Version: 2.1
Name: uplay
Version: 0.0.1
Summary: uplay tools
Home-page: UNKNOWN
Author: seal
Author-email: seal.xu@qq.com
License: UNKNOWN
Platform: UNKNOWN
Classifier: Programming Language :: Python :: 2
Classifier: License :: OSI Approved :: MIT License
Classifier: Operating System :: OS Independent
Requires-Python: >=2.7
